[
    {
        "YEAR": "III",
        "SEMESTER": "II",
        "CLASS INCHARGE NAME": "Dr.K.Siva Krishna",
        "SECTION": "ALPHA",
        "CONTACT NO.": "9966045723"
    },
    {
        "YEAR": "III",
        "SEMESTER": "II",
        "CLASS INCHARGE NAME": "M.Krishna Kishore",
        "SECTION": "BETA",
        "CONTACT NO.": "9848637090"
    },
    {
        "YEAR": "III",
        "SEMESTER": "II",
        "CLASS INCHARGE NAME": "Mrs.D.Sreevidya",
        "SECTION": "GEMMA",
        "CONTACT NO.": "8555874576"
    },
    {
        "YEAR": "III",
        "SEMESTER": "II",
        "CLASS INCHARGE NAME": "Dr.P.RamBabu",
        "SECTION": "DELTA",
        "CONTACT NO.": "9652665840"
    },
    {
        "YEAR": "III",
        "SEMESTER": "II",
        "CLASS INCHARGE NAME": "Mrs.B.Tejaswi",
        "SECTION": "SIGMA",
        "CONTACT NO.": "9059651369"
    }
]
